layerborn/cdk_iam_policy_builder_helper/_jsii/__init__.py
layerborn/cdk_iam_policy_builder_helper/_jsii/cdk-iam-policy-builder-helper@0.0.8.jsii.tgz
layerborn.cdk_iam_policy_builder_helper-0.0.8.dist-info/LICENSE
layerborn.cdk_iam_policy_builder_helper-0.0.8.dist-info/METADATA
layerborn.cdk_iam_policy_builder_helper-0.0.8.dist-info/WHEEL
layerborn.cdk_iam_policy_builder_helper-0.0.8.dist-info/top_level.txt
layerborn.cdk_iam_policy_builder_helper-0.0.8.dist-info/RECORD
