Metadata-Version: 2.1
Name: layerborn.cdk-iam-policy-builder-helper
Version: 0.0.8
Summary: A CDK construct that helps build IAM policies using the AWS IAM Policy Builder dump. Normally it is better to use cdk-iam-floyd, However, I found that cdk-iam-floyd currently is not jsii compliant so I wasn't able to use it in my jsii compliant projects in languages that are not typescript or python.
Home-page: https://github.com/layerborn/cdk-iam-policy-builder-helper-construct.git
Author: Jayson Rawlins<jayson.rawlins@layerborn.io>
License: Apache-2.0
Project-URL: Source, https://github.com/layerborn/cdk-iam-policy-builder-helper-construct.git
Classifier: Intended Audience :: Developers
Classifier: Operating System :: OS Independent
Classifier: Programming Language :: JavaScript
Classifier: Programming Language :: Python :: 3 :: Only
Classifier: Programming Language :: Python :: 3.8
Classifier: Programming Language :: Python :: 3.9
Classifier: Programming Language :: Python :: 3.10
Classifier: Programming Language :: Python :: 3.11
Classifier: Typing :: Typed
Classifier: Development Status :: 5 - Production/Stable
Classifier: License :: OSI Approved
Requires-Python: ~=3.8
License-File: LICENSE
Requires-Dist: aws-cdk-lib <3.0.0,>=2.80.0
Requires-Dist: constructs <11.0.0,>=10.3.0
Requires-Dist: jsii <2.0.0,>=1.98.0
Requires-Dist: projen <0.82.0,>=0.81.5
Requires-Dist: publication >=0.0.3
Requires-Dist: typeguard ~=2.13.3
